chimera_llm_proto/__init__.py
chimera_llm_proto/chimera_llm_pb2.py
chimera_llm_proto/chimera_llm_pb2.pyi
chimera_llm_proto/chimera_llm_pb2_grpc.py
chimera_llm_proto/tools.py
chimera_llm_proto-0.1.3.dist-info/METADATA
chimera_llm_proto-0.1.3.dist-info/WHEEL
chimera_llm_proto-0.1.3.dist-info/licenses/LICENSE
chimera_llm_proto-0.1.3.dist-info/RECORD
