Metadata-Version: 2.1
Name: chimera_llm_proto
Version: 0.1.3
Summary: chimera_llm_proto
Project-URL: Source, https://github.com/wh1isper/chimera_llm
Author-email: wh1isper <9573586@qq.com>
License: BSD 3-Clause License
License-File: LICENSE
Keywords: chimera_llm_proto
Classifier: Programming Language :: Python :: 3.8
Classifier: Programming Language :: Python :: 3.9
Classifier: Programming Language :: Python :: 3.10
Classifier: Programming Language :: Python :: 3.11
Requires-Python: >=3.8
Requires-Dist: grpcio>=1.51.0
Requires-Dist: protobuf>=4
